happy/__init__.py
happy/io.py
happy/local_config.py
happy/misc.py
happy/ndarray.py
happy/plots.py
happy_tools-1.0.0.dist-info/LICENSE.txt
happy_tools-1.0.0.dist-info/METADATA
happy_tools-1.0.0.dist-info/WHEEL
happy_tools-1.0.0.dist-info/top_level.txt
happy_tools-1.0.0.dist-info/RECORD
