Metadata-Version: 2.1
Name: happy-tools
Version: 1.0.0
Summary: Handy utilities to make everyday Python users happy.
Home-page: https://github.com/jankukacka/happy
Author: Jan Kukacka
License: MIT
Platform: UNKNOWN
Classifier: Programming Language :: Python :: 3
Classifier: License :: OSI Approved :: MIT License
Classifier: Operating System :: Microsoft :: Windows
Requires-Python: >=3.5
License-File: LICENSE.txt
Requires-Dist: matplotlib
Requires-Dist: numpy
Requires-Dist: scipy
